aprsd_slack_plugin/__init__.py
aprsd_slack_plugin/base_plugin.py
aprsd_slack_plugin/location_plugin.py
aprsd_slack_plugin/message_plugin.py
aprsd_slack_plugin/notify_plugin.py
aprsd_slack_plugin/conf/__init__.py
aprsd_slack_plugin/conf/opts.py
aprsd_slack_plugin/conf/slack.py
aprsd_slack_plugin-1.2.0.dist-info/LICENSE.txt
aprsd_slack_plugin-1.2.0.dist-info/METADATA
aprsd_slack_plugin-1.2.0.dist-info/WHEEL
aprsd_slack_plugin-1.2.0.dist-info/entry_points.txt
aprsd_slack_plugin-1.2.0.dist-info/pbr.json
aprsd_slack_plugin-1.2.0.dist-info/top_level.txt
aprsd_slack_plugin-1.2.0.dist-info/RECORD
